<!-- Indices written at Sun, 16 Dec 2012 21:49:11 MST -->

<datastore-indexes>

    <!-- Used 36 times in query history -->
    <datastore-index kind="event" ancestor="true" source="auto">
        <property name="archived" direction="asc"/>
        <property name="eventID" direction="asc"/>
    </datastore-index>

    <!-- Used 36 times in query history -->
    <datastore-index kind="game" ancestor="true" source="auto">
        <property name="eventID" direction="asc"/>
        <property name="gameID" direction="asc"/>
    </datastore-index>

    <!-- Used 34 times in query history -->
    <datastore-index kind="player" ancestor="true" source="auto">
        <property name="eventID" direction="asc"/>
        <property name="playerID" direction="desc"/>
    </datastore-index>

    <!-- Used 34 times in query history -->
    <datastore-index kind="score" ancestor="true" source="auto">
        <property name="eventID" direction="asc"/>
        <property name="gameID" direction="asc"/>
    </datastore-index>

    <!-- Used 2 times in query history -->
    <datastore-index kind="event" ancestor="true" source="auto">
        <property name="eventID" direction="asc"/>
    </datastore-index>

    <!-- Used 3 times in query history -->
    <datastore-index kind="event" ancestor="true" source="auto">
        <property name="eventID" direction="desc"/>
    </datastore-index>

    <!-- Used 2 times in query history -->
    <datastore-index kind="game" ancestor="true" source="auto">
        <property name="eventID" direction="desc"/>
        <property name="gameID" direction="desc"/>
    </datastore-index>

    <!-- Used 7 times in query history -->
    <datastore-index kind="player" ancestor="true" source="auto">
        <property name="eventID" direction="desc"/>
        <property name="playerID" direction="desc"/>
    </datastore-index>

    <!-- Used 16 times in query history -->
    <datastore-index kind="score" ancestor="true" source="auto">
        <property name="date" direction="desc"/>
    </datastore-index>

    <!-- Used 3 times in query history -->
    <datastore-index kind="name" ancestor="true" source="auto">
        <property name="Name" direction="asc"/>
    </datastore-index>

    <!-- Used 2 times in query history -->
    <datastore-index kind="text" ancestor="true" source="auto">
        <property name="date" direction="desc"/>
    </datastore-index>

    <!-- Used 13 times in query history -->
    <datastore-index kind="score" ancestor="true" source="auto">
        <property name="eventID" direction="asc"/>
        <property name="gameID" direction="asc"/>
        <property name="playerID" direction="asc"/>
        <property name="date" direction="desc"/>
    </datastore-index>

    <!-- Used 2 times in query history -->
    <datastore-index kind="event" ancestor="true" source="auto">
        <property name="active" direction="asc"/>
        <property name="eventID" direction="desc"/>
    </datastore-index>

</datastore-indexes>
